<?xml version="1.0" encoding="UTF-8"?>
<!-- Foundation -->
<window type="dialog" id="1197">
    <zorder>1</zorder>
	<defaultcontrol always="true">9000</defaultcontrol>
    <controls>
		<include>GlobalOverlay</include>
		<include>Animation.Common</include>		
		<control type="group">
			<centerleft>50%</centerleft>
			<centertop>50%</centertop>
			<width>468</width>
    		<top>230</top>
			<control type="image">
				<left>-9</left>
				<top>-20</top>		
				<right>9</right>
				<bottom>-14</bottom>
				<colordiffuse>White100</colordiffuse>
				<texture border="16">common/rounded-shadow8.png</texture>
			</control>	
			<control type="group">
				<left>22</left>
				<top>0</top>
				<control type="label">
					<description>Header Label</description>
					<left>70</left>
					<width>1000</width>
					<posy>0</posy>
					<include>FontTop</include>
					<textcolor>Dark2</textcolor>
					<label>5</label>
				</control>
				
				<control type="image">
					<top>15</top>
					<left>15</left>
					<width>40</width>
					<height>40</height>
					<colordiffuse>$VAR[ColorKodiLogo]</colordiffuse>
					<texture>buttons/kodi-logo.png</texture>
				</control>
				
				<!-- Lines -->
				<control type="image">
					<top>70</top>
					<left>17</left>
					<width>385</width>
					<height>1</height>
					<bottom>10</bottom>
					<colordiffuse>Black12</colordiffuse>
					<texture>common/white.png</texture>
				</control>
			</control>		
			<control type="grouplist" id="9000">
				<top>90</top>
				<control type="radiobutton" id="93">         
                    <description>Filter</description>
                    <include>DefContextButton</include>
                    <label>31214</label>
                    <align>left</align>
                    <selected>Skin.HasSetting(osd.showplot)</selected>
                    <onclick>Skin.ToggleSetting(osd.showplot)</onclick>
					<onright>Dialog.Close(1197)</onright>
					<onleft>Dialog.Close(1197)</onleft>
                </control>
				<control type="radiobutton" id="94">                    
                    <description>Filter</description>
                    <include>DefContextButton</include>			
                    <label>31154</label>
                    <align>left</align>
                    <selected>Skin.HasSetting(furniture.flagiconsosd)</selected>
                    <onclick>Skin.ToggleSetting(furniture.flagiconsosd)</onclick>
					<onright>Dialog.Close(1197)</onright>
					<onleft>Dialog.Close(1197)</onleft>
                </control>
				<control type="radiobutton" id="95">                  
                    <description>Filter</description>
                    <include>DefContextButton</include>
                    <label>31246</label>
                    <align>left</align>
                    <selected>Skin.HasSetting(furniture.flagiconsosdnoicons)</selected>
                    <onclick>Skin.ToggleSetting(furniture.flagiconsosdnoicons)</onclick>
					<onright>Dialog.Close(1197)</onright>
					<onleft>Dialog.Close(1197)</onleft>
					<enable>Skin.HasSetting(furniture.flagiconsosd)</enable>
                </control>
				<control type="radiobutton" id="96">                 
                    <description>Handlung</description>
                    <include>DefContextButton</include>
                    <label>31218</label>
                    <align>left</align>
                    <selected>Skin.HasSetting(videoosd.numericrating)</selected>
                    <onclick>Skin.ToggleSetting(videoosd.numericrating)</onclick>
					<onright>Dialog.Close(1197)</onright>
					<onleft>Dialog.Close(1197)</onleft>
					<enable>!VideoPlayer.Content(livetv)</enable>
                </control>
				<control type="radiobutton" id="97">
					<textwidth>350</textwidth>                 
                    <description>Handlung</description>
                    <include>DefContextButton</include>
                    <label>37521</label>
                    <align>left</align>
                    <selected>Skin.HasSetting(osd.coloredicons)</selected>
                    <onclick>Skin.ToggleSetting(osd.coloredicons)</onclick>
					<onright>Dialog.Close(1197)</onright>
					<onleft>Dialog.Close(1197)</onleft>					
					<enable>Skin.HasSetting(furniture.flagiconsosd)</enable>
                </control>
				<control type="radiobutton" id="98" description="Match theme">					
                    <include>DefContextButton</include>
                    <align>left</align>
					<label>37609</label>
					<selected>Skin.HasSetting(osd.usethemeNewOSD)</selected>
					<onclick>Skin.ToggleSetting(osd.usethemeNewOSD)</onclick>
					<onright>Dialog.Close(1197)</onright>
					<onleft>Dialog.Close(1197)</onleft>
				</control>
				<control type="radiobutton" id="99">                   
                    <include>DefContextButton</include>
                    <label>37549</label>
                    <align>left</align>
                    <selected>Skin.HasSetting(pvr.showtechnicalinfo)</selected>
                    <onclick>Skin.ToggleSetting(pvr.showtechnicalinfo)</onclick>
					<onright>Dialog.Close(1197)</onright>
					<onleft>Dialog.Close(1197)</onleft>					
					<enable>VideoPlayer.Content(livetv)</enable>
                </control>
				<control type="radiobutton" id="100">                   
                    <description>Filter</description>
                    <include>DefContextButton</include>
                    <label>31153</label>
                    <align>left</align>
                    <selected>Skin.HasSetting(ClockOSD)</selected>
                    <onclick>Skin.ToggleSetting(ClockOSD)</onclick>
					<onright>Dialog.Close(1197)</onright>
					<onleft>Dialog.Close(1197)</onleft>
                </control>
            </control>
		</control>
    </controls>
</window>
